debugtrace/__init__.py
debugtrace/_print.py
debugtrace/config.py
debugtrace/log_buffer.py
debugtrace/loggers.py
debugtrace/main.py
debugtrace/state.py
debugtrace/version.py
debugtrace-1.5.0.dist-info/licenses/LICENSE
debugtrace-1.5.0.dist-info/METADATA
debugtrace-1.5.0.dist-info/WHEEL
debugtrace-1.5.0.dist-info/top_level.txt
debugtrace-1.5.0.dist-info/RECORD
