Metadata-Version: 2.4
Name: debugtrace
Version: 1.5.0
Summary: Output trace logs when debugging Python programs
Home-page: https://github.com/MasatoKokubo/DebugTrace-py
Author: Masato Kokubo
Author-email: masatokokubo@gmail.com
Maintainer: Masato Kokubo
Maintainer-email: masatokokubo@gmail.com
License: MIT
Classifier: Development Status :: 5 - Production/Stable
Classifier: Programming Language :: Python :: 3.7
Classifier: License :: OSI Approved :: MIT License
License-File: LICENSE
Dynamic: author
Dynamic: author-email
Dynamic: classifier
Dynamic: description
Dynamic: description-content-type
Dynamic: home-page
Dynamic: license
Dynamic: license-file
Dynamic: maintainer
Dynamic: maintainer-email
Dynamic: summary
